MANIFEST.in
setup.py
bin/ccm_widgets
ccm_widgets/BaseWidget.py
ccm_widgets/__init__.py
ccm_widgets/_version.py
ccm_widgets/all_widgets.py
ccm_widgets/host_widget.py
ccm_widgets/init.py
ccm_widgets/reactopyacolabwidget.py
ccm_widgets/reactopyacomponent.py
ccm_widgets/reactopyaelectronwidget.py
ccm_widgets/reactopyahostedwidget.py
ccm_widgets/shellscript.py
ccm_widgets.egg-info/PKG-INFO
ccm_widgets.egg-info/SOURCES.txt
ccm_widgets.egg-info/dependency_links.txt
ccm_widgets.egg-info/requires.txt
ccm_widgets.egg-info/top_level.txt
ccm_widgets/dist/bundle.js
ccm_widgets/electron/src/ReactopyaModel.js
ccm_widgets/electron/src/index.js
ccm_widgets/electron/src/preload.js
ccm_widgets/electron/web/index.html
ccm_widgets/host_widget/dist/bundle.js
ccm_widgets/widgets/__init__.py
ccm_widgets/widgets/create_sync.py
ccm_widgets/widgets/index.js
ccm_widgets/widgets/jupyter.py
ccm_widgets/widgets/reactopya.config.json
ccm_widgets/widgets/Accordion/Accordion.js
ccm_widgets/widgets/Accordion/Accordion.json
ccm_widgets/widgets/Accordion/Accordion.py
ccm_widgets/widgets/Accordion/AccordionStyle.css
ccm_widgets/widgets/Accordion/__init__.py
ccm_widgets/widgets/Accordion/__pycache__/Accordion.cpython-36.pyc
ccm_widgets/widgets/Accordion/__pycache__/Accordion.cpython-37.pyc
ccm_widgets/widgets/Accordion/__pycache__/__init__.cpython-36.pyc
ccm_widgets/widgets/Accordion/__pycache__/__init__.cpython-37.pyc
ccm_widgets/widgets/Clustering/Clustering.js
ccm_widgets/widgets/Clustering/Clustering.json
ccm_widgets/widgets/Clustering/Clustering.py
ccm_widgets/widgets/Clustering/__init__.py
ccm_widgets/widgets/Clustering/clustering_datasets.json
ccm_widgets/widgets/Clustering/generateColorTable.js
ccm_widgets/widgets/Clustering/test_clustering.py
ccm_widgets/widgets/Clustering/tmp.py
ccm_widgets/widgets/Clustering/__pycache__/Clustering.cpython-36.pyc
ccm_widgets/widgets/Clustering/__pycache__/__init__.cpython-36.pyc
ccm_widgets/widgets/HBox/HBox.js
ccm_widgets/widgets/HBox/HBox.json
ccm_widgets/widgets/HBox/HBox.py
ccm_widgets/widgets/HBox/__init__.py
ccm_widgets/widgets/HBox/__pycache__/HBox.cpython-36.pyc
ccm_widgets/widgets/HBox/__pycache__/HBox.cpython-37.pyc
