Metadata-Version: 1.1
Name: ccm-widgets
Version: 0.4.11
Summary: Reactopya widgets of relevance to the Center for Computational Mathematics, Flatiron Institute
Home-page: UNKNOWN
Author: Jeremy Magland
Author-email: UNKNOWN
License: UNKNOWN
Platform: UNKNOWN
Classifier: Programming Language :: Python :: 3
Classifier: License :: OSI Approved :: Apache Software License
Classifier: Operating System :: OS Independent
